README.md
setup.py
TextualConfig/__dependence__.py
TextualConfig/__init__.py
TextualConfig/__main__.py
TextualConfig/demo.css
TextualConfig/main.py
TextualConfig/src.py
TextualConfig.egg-info/PKG-INFO
TextualConfig.egg-info/SOURCES.txt
TextualConfig.egg-info/dependency_links.txt
TextualConfig.egg-info/requires.txt
TextualConfig.egg-info/top_level.txt
TextualConfig.egg-info/zip-safe