Metadata-Version: 2.1
Name: TextualConfig
Version: 0.0.4
Summary: A Config Tool with Textual support.
Home-page: https://github.com/Rhythmicc/TextualConfig
Author: RhythmLian
License: MIT
Keywords: Textual Config
Classifier: Programming Language :: Python :: 3
Classifier: License :: OSI Approved :: MIT License
Classifier: Operating System :: OS Independent
